odoo/addons/account_cutoff_accrual_picking/README.rst
odoo/addons/account_cutoff_accrual_picking/__init__.py
odoo/addons/account_cutoff_accrual_picking/__manifest__.py
odoo/addons/account_cutoff_accrual_picking/i18n/account_cutoff_accrual_picking.pot
odoo/addons/account_cutoff_accrual_picking/i18n/de.po
odoo/addons/account_cutoff_accrual_picking/i18n/fr.po
odoo/addons/account_cutoff_accrual_picking/i18n/pt.po
odoo/addons/account_cutoff_accrual_picking/i18n/pt_BR.po
odoo/addons/account_cutoff_accrual_picking/images/accrued_expense_done.jpg
odoo/addons/account_cutoff_accrual_picking/images/accrued_expense_draft.jpg
odoo/addons/account_cutoff_accrual_picking/images/accrued_expense_journal_entry.jpg
odoo/addons/account_cutoff_accrual_picking/models/__init__.py
odoo/addons/account_cutoff_accrual_picking/models/account_cutoff.py
odoo/addons/account_cutoff_accrual_picking/readme/CONFIGURE.rst
odoo/addons/account_cutoff_accrual_picking/readme/CONTRIBUTORS.rst
odoo/addons/account_cutoff_accrual_picking/readme/DESCRIPTION.rst
odoo/addons/account_cutoff_accrual_picking/static/description/icon.png
odoo/addons/account_cutoff_accrual_picking/static/description/index.html
odoo/addons/account_cutoff_accrual_picking/static/src/img/icon.png
odoo12_addon_account_cutoff_accrual_picking-12.0.1.0.0.99.dev12.dist-info/METADATA
odoo12_addon_account_cutoff_accrual_picking-12.0.1.0.0.99.dev12.dist-info/WHEEL
odoo12_addon_account_cutoff_accrual_picking-12.0.1.0.0.99.dev12.dist-info/top_level.txt
odoo12_addon_account_cutoff_accrual_picking-12.0.1.0.0.99.dev12.dist-info/RECORD
